[
  {
    "ecli": "ECLI:CE:ECHR:1995:0323JUD001531889",
    "references": []
  },
  {
    "ecli": "ECLI:CE:ECHR:1997:0925JUD002317894",
    "references": []
  },
  {
    "ecli": "ECLI:CE:ECHR:1999:0708JUD002365794",
    "references": []
  },
  {
    "ecli": "ECLI:CE:ECHR:1999:0708JUD002376394",
    "references": []
  },
  {
    "ecli": "ECLI:CE:ECHR:1999:0928JUD002247993",
    "references": []
  },
  {
    "ecli": "ECLI:CE:ECHR:1999:0928JUD002811495",
    "references": []
  },
  {
    "ecli": "ECLI:CE:ECHR:1999:1028JUD002834295",
    "references": []
  },
  {
    "ecli": "ECLI:CE:ECHR:1999:1208JUD002388594",
    "references": []
  },
  {
    "ecli": "ECLI:CE:ECHR:2000:0406JUD002677295",
    "references": [
      "ECLI:CE:ECHR:1999:0928JUD002811495"
    ]
  },
  {
    "ecli": "ECLI:CE:ECHR:2000:0504JUD002834195",
    "references": [
      "ECLI:CE:ECHR:1999:0928JUD002811495",
      "ECLI:CE:ECHR:1999:0708JUD002365794"
    ]
  },
  {
    "ecli": "ECLI:CE:ECHR:2000:0627JUD002227793",
    "references": [
      "ECLI:CE:ECHR:1999:0708JUD002365794",
      "ECLI:CE:ECHR:2000:0406JUD002677295"
    ]
  },
  {
    "ecli": "ECLI:CE:ECHR:2000:0627JUD002198693",
    "references": [
      "ECLI:CE:ECHR:1999:0708JUD002365794"
    ]
  },
  {
    "ecli": "ECLI:CE:ECHR:2002:1024JUD003673297",
    "references": [
      "ECLI:CE:ECHR:2000:0627JUD002227793",
      "ECLI:CE:ECHR:1999:0928JUD002811495"
    ]
  },
  {
    "ecli": "ECLI:CE:ECHR:2003:0731JUD001621990",
    "references": [
      "ECLI:CE:ECHR:1995:0323JUD001531889",
      "ECLI:CE:ECHR:2002:1024JUD003673297"
    ]
  },
  {
    "ecli": "ECLI:CE:ECHR:2004:0708JUD004878799",
    "references": [
      "ECLI:CE:ECHR:2000:0627JUD002198693",
      "ECLI:CE:ECHR:2000:0406JUD002677295"
    ]
  },
  {
    "ecli": "ECLI:CE:ECHR:2005:0204JUD004682799",
    "references": [
      "ECLI:CE:ECHR:2004:0708JUD004878799"
    ]
  },
  {
    "ecli": "ECLI:CE:ECHR:2005:0210JUD003380802",
    "references": []
  },
  {
    "ecli": "ECLI:CE:ECHR:2005:0419JUD007268601",
    "references": []
  },
  {
    "ecli": "ECLI:CE:ECHR:2005:0512JUD004622199",
    "references": [
      "ECLI:CE:ECHR:2000:0627JUD002198693",
      "ECLI:CE:ECHR:2000:0504JUD002834195",
      "ECLI:CE:ECHR:1999:1028JUD002834295"
    ]
  },
  {
    "ecli": "ECLI:CE:ECHR:2006:0117JUD002566402",
    "references": []
  },
  {
    "ecli": "ECLI:CE:ECHR:2006:0316JUD005827800",
    "references": [
      "ECLI:CE:ECHR:1999:1208JUD002388594",
      "ECLI:CE:ECHR:2000:0406JUD002677295",
      "ECLI:CE:ECHR:2004:0708JUD004878799",
      "ECLI:CE:ECHR:1999:0928JUD002811495"
    ]
  },
  {
    "ecli": "ECLI:CE:ECHR:2006:0329JUD003681397",
    "references": [
      "ECLI:CE:ECHR:1999:1028JUD002834295",
      "ECLI:CE:ECHR:1999:0928JUD002811495"
    ]
  },
  {
    "ecli": "ECLI:CE:ECHR:2006:0329JUD006236100",
    "references": [
      "ECLI:CE:ECHR:2006:0329JUD006510201",
      "ECLI:CE:ECHR:2006:0329JUD003681397",
      "ECLI:CE:ECHR:2006:0329JUD006489001",
      "ECLI:CE:ECHR:2006:0329JUD006489701",
      "ECLI:CE:ECHR:2006:0329JUD006470501",
      "ECLI:CE:ECHR:2006:0329JUD006507501",
      "ECLI:CE:ECHR:2004:0708JUD004878799",
      "ECLI:CE:ECHR:2006:0329JUD006469901",
      "ECLI:CE:ECHR:1999:0928JUD002811495"
    ]
  },
  {
    "ecli": "ECLI:CE:ECHR:2006:0329JUD006469901",
    "references": [
      "ECLI:CE:ECHR:2006:0329JUD006236100",
      "ECLI:CE:ECHR:2006:0329JUD006510201",
      "ECLI:CE:ECHR:2006:0329JUD003681397",
      "ECLI:CE:ECHR:2006:0329JUD006489001",
      "ECLI:CE:ECHR:2006:0329JUD006489701",
      "ECLI:CE:ECHR:2006:0329JUD006470501",
      "ECLI:CE:ECHR:2006:0329JUD006507501",
      "ECLI:CE:ECHR:2004:0708JUD004878799",
      "ECLI:CE:ECHR:1999:0928JUD002811495"
    ]
  },
  {
    "ecli": "ECLI:CE:ECHR:2006:0329JUD006470501",
    "references": [
      "ECLI:CE:ECHR:2006:0329JUD006236100",
      "ECLI:CE:ECHR:2006:0329JUD006510201",
      "ECLI:CE:ECHR:2006:0329JUD003681397",
      "ECLI:CE:ECHR:2006:0329JUD006489001",
      "ECLI:CE:ECHR:2006:0329JUD006489701",
      "ECLI:CE:ECHR:2006:0329JUD006507501",
      "ECLI:CE:ECHR:2004:0708JUD004878799",
      "ECLI:CE:ECHR:2006:0329JUD006469901",
      "ECLI:CE:ECHR:1999:0928JUD002811495"
    ]
  },
  {
    "ecli": "ECLI:CE:ECHR:2006:0329JUD006507501",
    "references": [
      "ECLI:CE:ECHR:2006:0329JUD006236100",
      "ECLI:CE:ECHR:2006:0329JUD006510201",
      "ECLI:CE:ECHR:2006:0329JUD003681397",
      "ECLI:CE:ECHR:2006:0329JUD006489001",
      "ECLI:CE:ECHR:2006:0329JUD006489701",
      "ECLI:CE:ECHR:2006:0329JUD006470501",
      "ECLI:CE:ECHR:2004:0708JUD004878799",
      "ECLI:CE:ECHR:2006:0329JUD006469901",
      "ECLI:CE:ECHR:1999:0928JUD002811495"
    ]
  },
  {
    "ecli": "ECLI:CE:ECHR:2006:0329JUD006489701",
    "references": [
      "ECLI:CE:ECHR:2006:0329JUD006236100",
      "ECLI:CE:ECHR:2006:0329JUD006510201",
      "ECLI:CE:ECHR:2006:0329JUD003681397",
      "ECLI:CE:ECHR:2006:0329JUD006489001",
      "ECLI:CE:ECHR:2006:0329JUD006470501",
      "ECLI:CE:ECHR:2006:0329JUD006507501",
      "ECLI:CE:ECHR:2004:0708JUD004878799",
      "ECLI:CE:ECHR:2006:0329JUD006469901",
      "ECLI:CE:ECHR:1999:0928JUD002811495"
    ]
  },
  {
    "ecli": "ECLI:CE:ECHR:2006:0329JUD006489001",
    "references": [
      "ECLI:CE:ECHR:2006:0329JUD006236100",
      "ECLI:CE:ECHR:2006:0329JUD006510201",
      "ECLI:CE:ECHR:2006:0329JUD003681397",
      "ECLI:CE:ECHR:2006:0329JUD006489701",
      "ECLI:CE:ECHR:2006:0329JUD006470501",
      "ECLI:CE:ECHR:2006:0329JUD006507501",
      "ECLI:CE:ECHR:2004:0708JUD004878799",
      "ECLI:CE:ECHR:2006:0329JUD006469901",
      "ECLI:CE:ECHR:1999:0928JUD002811495"
    ]
  },
  {
    "ecli": "ECLI:CE:ECHR:2006:0329JUD006510201",
    "references": [
      "ECLI:CE:ECHR:2006:0329JUD006236100",
      "ECLI:CE:ECHR:2006:0329JUD003681397",
      "ECLI:CE:ECHR:2006:0329JUD006489001",
      "ECLI:CE:ECHR:2006:0329JUD006489701",
      "ECLI:CE:ECHR:2006:0329JUD006470501",
      "ECLI:CE:ECHR:2006:0329JUD006507501",
      "ECLI:CE:ECHR:2004:0708JUD004878799",
      "ECLI:CE:ECHR:2006:0329JUD006469901",
      "ECLI:CE:ECHR:1999:0928JUD002811495"
    ]
  },
  {
    "ecli": "ECLI:CE:ECHR:2006:1207JUD004311604",
    "references": []
  },
  {
    "ecli": "ECLI:CE:ECHR:2007:0115JUD006065400",
    "references": [
      "ECLI:CE:ECHR:1999:0928JUD002811495",
      "ECLI:CE:ECHR:1999:1028JUD002834295",
      "ECLI:CE:ECHR:2000:0627JUD002198693",
      "ECLI:CE:ECHR:2004:0708JUD004878799",
      "ECLI:CE:ECHR:1999:0708JUD002376394",
      "ECLI:CE:ECHR:2000:0406JUD002677295",
      "ECLI:CE:ECHR:2002:1024JUD003673297"
    ]
  },
  {
    "ecli": "ECLI:CE:ECHR:2007:0412JUD006645501",
    "references": []
  },
  {
    "ecli": "ECLI:CE:ECHR:2007:1220JUD002552503",
    "references": [
      "ECLI:CE:ECHR:1999:0928JUD002811495",
      "ECLI:CE:ECHR:2000:0406JUD002677295",
      "ECLI:CE:ECHR:2002:1024JUD003673297",
      "ECLI:CE:ECHR:2004:0708JUD004878799",
      "ECLI:CE:ECHR:2007:0115JUD006065400"
    ]
  },
  {
    "ecli": "ECLI:CE:ECHR:2008:0429JUD001337805",
    "references": []
  },
  {
    "ecli": "ECLI:CE:ECHR:2008:1003JUD004457498",
    "references": [
      "ECLI:CE:ECHR:2002:1024JUD003673297",
      "ECLI:CE:ECHR:2007:1220JUD002552503",
      "ECLI:CE:ECHR:2007:0115JUD006065400",
      "ECLI:CE:ECHR:2000:0627JUD002227793"
    ]
  },
  {
    "ecli": "ECLI:CE:ECHR:2009:0310JUD003980605",
    "references": [
      "ECLI:CE:ECHR:1999:0708JUD002376394",
      "ECLI:CE:ECHR:2004:0708JUD004878799"
    ]
  },
  {
    "ecli": "ECLI:CE:ECHR:2009:0716JUD002008202",
    "references": []
  },
  {
    "ecli": "ECLI:CE:ECHR:2009:1015JUD001705606",
    "references": [
      "ECLI:CE:ECHR:1999:0928JUD002811495",
      "ECLI:CE:ECHR:2008:0429JUD001337805"
    ]
  },
  {
    "ecli": "ECLI:CE:ECHR:2010:0930JUD004491708",
    "references": [
      "ECLI:CE:ECHR:2000:0406JUD002677295"
    ]
  },
  {
    "ecli": "ECLI:CE:ECHR:2010:1102JUD002127203",
    "references": [
      "ECLI:CE:ECHR:2005:0512JUD004622199",
      "ECLI:CE:ECHR:2006:0329JUD006510201",
      "ECLI:CE:ECHR:2006:0329JUD003681397",
      "ECLI:CE:ECHR:2008:0429JUD001337805"
    ]
  },
  {
    "ecli": "ECLI:CE:ECHR:2009:1222JUD002799606",
    "references": [
      "ECLI:CE:ECHR:2008:0429JUD001337805",
      "ECLI:CE:ECHR:2006:0316JUD005827800"
    ]
  },
  {
    "ecli": "ECLI:CE:ECHR:2010:0427JUD000000708",
    "references": [
      "ECLI:CE:ECHR:2006:0316JUD005827800",
      "ECLI:CE:ECHR:2008:0429JUD001337805"
    ]
  },
  {
    "ecli": "ECLI:CE:ECHR:2010:0520JUD002440202",
    "references": []
  },
  {
    "ecli": "ECLI:CE:ECHR:2010:0520JUD004227608",
    "references": [
      "ECLI:CE:ECHR:2006:0329JUD003681397"
    ]
  },
  {
    "ecli": "ECLI:CE:ECHR:2010:0601JUD002297805",
    "references": [
      "ECLI:CE:ECHR:1999:0928JUD002811495",
      "ECLI:CE:ECHR:2006:0329JUD003681397",
      "ECLI:CE:ECHR:2000:0406JUD002677295"
    ]
  },
  {
    "ecli": "ECLI:CE:ECHR:2011:0121JUD003069609",
    "references": [
      "ECLI:CE:ECHR:2005:0512JUD004622199",
      "ECLI:CE:ECHR:1999:0708JUD002365794",
      "ECLI:CE:ECHR:2000:0406JUD002677295",
      "ECLI:CE:ECHR:2009:0310JUD003980605"
    ]
  },
  {
    "ecli": "ECLI:CE:ECHR:2011:0707JUD005572107",
    "references": [
      "ECLI:CE:ECHR:1999:0708JUD002376394",
      "ECLI:CE:ECHR:2005:0512JUD004622199",
      "ECLI:CE:ECHR:2004:0708JUD004878799"
    ]
  },
  {
    "ecli": "ECLI:CE:ECHR:2011:1215JUD002563405",
    "references": []
  },
  {
    "ecli": "ECLI:CE:ECHR:2012:0223JUD002776509",
    "references": [
      "ECLI:CE:ECHR:2005:0512JUD004622199",
      "ECLI:CE:ECHR:2011:0121JUD003069609",
      "ECLI:CE:ECHR:2011:0707JUD005572107",
      "ECLI:CE:ECHR:2004:0708JUD004878799"
    ]
  },
  {
    "ecli": "ECLI:CE:ECHR:2012:0315JUD000414904",
    "references": [
      "ECLI:CE:ECHR:2010:0427JUD000000708",
      "ECLI:CE:ECHR:2009:1015JUD001705606",
      "ECLI:CE:ECHR:2008:0429JUD001337805"
    ]
  },
  {
    "ecli": "ECLI:CE:ECHR:2012:0322JUD003007806",
    "references": [
      "ECLI:CE:ECHR:2002:1024JUD003673297",
      "ECLI:CE:ECHR:2009:0310JUD003980605",
      "ECLI:CE:ECHR:2011:0121JUD003069609",
      "ECLI:CE:ECHR:2010:1102JUD002127203",
      "ECLI:CE:ECHR:2007:0115JUD006065400",
      "ECLI:CE:ECHR:2000:0627JUD002227793",
      "ECLI:CE:ECHR:1999:0708JUD002376394",
      "ECLI:CE:ECHR:1999:0928JUD002811495"
    ]
  },
  {
    "ecli": "ECLI:CE:ECHR:2012:0626JUD002682806",
    "references": [
      "ECLI:CE:ECHR:2006:0329JUD003681397",
      "ECLI:CE:ECHR:2012:0322JUD003007806",
      "ECLI:CE:ECHR:2010:0601JUD002297805",
      "ECLI:CE:ECHR:2003:0731JUD001621990",
      "ECLI:CE:ECHR:2007:0115JUD006065400",
      "ECLI:CE:ECHR:1999:0928JUD002811495",
      "ECLI:CE:ECHR:2010:1102JUD002127203",
      "ECLI:CE:ECHR:2011:0121JUD003069609"
    ]
  },
  {
    "ecli": "ECLI:CE:ECHR:2012:0731JUD004002003",
    "references": [
      "ECLI:CE:ECHR:2005:0512JUD004622199",
      "ECLI:CE:ECHR:1999:0708JUD002365794"
    ]
  },
  {
    "ecli": "ECLI:CE:ECHR:2012:0912JUD001059308",
    "references": [
      "ECLI:CE:ECHR:1999:1028JUD002834295",
      "ECLI:CE:ECHR:2010:0601JUD002297805",
      "ECLI:CE:ECHR:2011:0707JUD005572107",
      "ECLI:CE:ECHR:2004:0708JUD004878799"
    ]
  },
  {
    "ecli": "ECLI:CE:ECHR:2012:1213JUD002268907",
    "references": [
      "ECLI:CE:ECHR:2011:0121JUD003069609",
      "ECLI:CE:ECHR:2012:0223JUD002776509",
      "ECLI:CE:ECHR:2000:0504JUD002834195",
      "ECLI:CE:ECHR:1999:0708JUD002365794"
    ]
  },
  {
    "ecli": "ECLI:CE:ECHR:2013:0709JUD000233009",
    "references": [
      "ECLI:CE:ECHR:2000:0504JUD002834195"
    ]
  },
  {
    "ecli": "ECLI:CE:ECHR:2013:1021JUD005550807",
    "references": [
      "ECLI:CE:ECHR:1999:0708JUD002365794",
      "ECLI:CE:ECHR:1999:0928JUD002811495",
      "ECLI:CE:ECHR:2004:0708JUD004878799",
      "ECLI:CE:ECHR:2012:0912JUD001059308",
      "ECLI:CE:ECHR:2000:0406JUD002677295",
      "ECLI:CE:ECHR:1999:0708JUD002376394",
      "ECLI:CE:ECHR:2011:0707JUD005572107"
    ]
  },
  {
    "ecli": "ECLI:CE:ECHR:2013:1107JUD002938109",
    "references": [
      "ECLI:CE:ECHR:2010:0427JUD000000708",
      "ECLI:CE:ECHR:2008:0429JUD001337805"
    ]
  },
  {
    "ecli": "ECLI:CE:ECHR:2014:0128JUD003581009",
    "references": [
      "ECLI:CE:ECHR:2010:0601JUD002297805",
      "ECLI:CE:ECHR:1999:0928JUD002811495",
      "ECLI:CE:ECHR:2006:0329JUD003681397"
    ]
  },
  {
    "ecli": "ECLI:CE:ECHR:2014:0624JUD002732906",
    "references": []
  },
  {
    "ecli": "ECLI:CE:ECHR:2014:0701JUD004383511",
    "references": [
      "ECLI:CE:ECHR:2012:0322JUD003007806",
      "ECLI:CE:ECHR:2008:0429JUD001337805"
    ]
  },
  {
    "ecli": "ECLI:CE:ECHR:2014:0717JUD004784808",
    "references": [
      "ECLI:CE:ECHR:2009:1015JUD001705606",
      "ECLI:CE:ECHR:1999:0928JUD002811495",
      "ECLI:CE:ECHR:2012:0322JUD003007806",
      "ECLI:CE:ECHR:1999:0708JUD002365794",
      "ECLI:CE:ECHR:2011:0707JUD005572107",
      "ECLI:CE:ECHR:2005:0512JUD004622199",
      "ECLI:CE:ECHR:2000:0627JUD002227793",
      "ECLI:CE:ECHR:2012:1213JUD002268907",
      "ECLI:CE:ECHR:1999:1028JUD002834295",
      "ECLI:CE:ECHR:2008:0429JUD001337805"
    ]
  },
  {
    "ecli": "ECLI:CE:ECHR:2014:0717JUD003254108",
    "references": [
      "ECLI:CE:ECHR:2012:0322JUD003007806",
      "ECLI:CE:ECHR:2005:0512JUD004622199",
      "ECLI:CE:ECHR:2000:0406JUD002677295",
      "ECLI:CE:ECHR:2010:0601JUD002297805",
      "ECLI:CE:ECHR:2009:1015JUD001705606",
      "ECLI:CE:ECHR:2011:0121JUD003069609"
    ]
  },
  {
    "ecli": "ECLI:CE:ECHR:2014:1023JUD001723913",
    "references": [
      "ECLI:CE:ECHR:2012:0223JUD002776509",
      "ECLI:CE:ECHR:2012:1213JUD002268907",
      "ECLI:CE:ECHR:1999:0708JUD002376394",
      "ECLI:CE:ECHR:2006:0329JUD003681397"
    ]
  },
  {
    "ecli": "ECLI:CE:ECHR:2015:0414JUD002401405",
    "references": [
      "ECLI:CE:ECHR:2006:0329JUD003681397",
      "ECLI:CE:ECHR:2010:0601JUD002297805",
      "ECLI:CE:ECHR:2000:0627JUD002198693",
      "ECLI:CE:ECHR:2011:0707JUD005572107",
      "ECLI:CE:ECHR:2012:0626JUD002682806",
      "ECLI:CE:ECHR:1999:0708JUD002376394",
      "ECLI:CE:ECHR:2014:0717JUD004784808",
      "ECLI:CE:ECHR:2009:1015JUD001705606"
    ]
  },
  {
    "ecli": "ECLI:CE:ECHR:2015:0605JUD004604314",
    "references": [
      "ECLI:CE:ECHR:2000:0627JUD002227793",
      "ECLI:CE:ECHR:2014:0717JUD004784808"
    ]
  },
  {
    "ecli": "ECLI:CE:ECHR:2015:0616JUD001321605",
    "references": [
      "ECLI:CE:ECHR:2011:0707JUD005572107",
      "ECLI:CE:ECHR:2015:0616JUD004016706",
      "ECLI:CE:ECHR:2004:0708JUD004878799"
    ]
  },
  {
    "ecli": "ECLI:CE:ECHR:2015:0616JUD004016706",
    "references": [
      "ECLI:CE:ECHR:2011:0707JUD005572107",
      "ECLI:CE:ECHR:2011:0121JUD003069609",
      "ECLI:CE:ECHR:2015:0616JUD001321605",
      "ECLI:CE:ECHR:2014:0717JUD004784808",
      "ECLI:CE:ECHR:2004:0708JUD004878799"
    ]
  },
  {
    "ecli": "ECLI:CE:ECHR:2015:0827JUD004647011",
    "references": [
      "ECLI:CE:ECHR:2006:0329JUD003681397",
      "ECLI:CE:ECHR:2014:0701JUD004383511"
    ]
  },
  {
    "ecli": "ECLI:CE:ECHR:2015:1204JUD004714306",
    "references": [
      "ECLI:CE:ECHR:2014:0717JUD004784808",
      "ECLI:CE:ECHR:1999:1028JUD002834295",
      "ECLI:CE:ECHR:2000:0504JUD002834195"
    ]
  },
  {
    "ecli": "ECLI:CE:ECHR:2016:0218JUD001072213",
    "references": [
      "ECLI:CE:ECHR:2006:0329JUD003681397",
      "ECLI:CE:ECHR:1999:0928JUD002811495"
    ]
  },
  {
    "ecli": "ECLI:CE:ECHR:2016:0426JUD001051110",
    "references": [
      "ECLI:CE:ECHR:2007:0115JUD006065400",
      "ECLI:CE:ECHR:2006:0329JUD006489701",
      "ECLI:CE:ECHR:2012:0912JUD001059308",
      "ECLI:CE:ECHR:2011:0121JUD003069609",
      "ECLI:CE:ECHR:2010:0601JUD002297805"
    ]
  },
  {
    "ecli": "ECLI:CE:ECHR:2016:0705JUD002375507",
    "references": [
      "ECLI:CE:ECHR:2004:0708JUD004878799",
      "ECLI:CE:ECHR:2000:0406JUD002677295"
    ]
  },
  {
    "ecli": "ECLI:CE:ECHR:2016:0705JUD004489810",
    "references": [
      "ECLI:CE:ECHR:2015:0616JUD001321605",
      "ECLI:CE:ECHR:2015:0414JUD002401405",
      "ECLI:CE:ECHR:2010:0601JUD002297805",
      "ECLI:CE:ECHR:2000:0406JUD002677295"
    ]
  },
  {
    "ecli": "ECLI:CE:ECHR:2016:1004JUD001264615",
    "references": [
      "ECLI:CE:ECHR:2009:0310JUD003980605",
      "ECLI:CE:ECHR:2016:0426JUD001051110",
      "ECLI:CE:ECHR:2010:0930JUD004491708"
    ]
  },
  {
    "ecli": "ECLI:CE:ECHR:2016:1006JUD007386410",
    "references": []
  },
  {
    "ecli": "ECLI:CE:ECHR:2017:0627JUD000093113",
    "references": [
      "ECLI:CE:ECHR:2016:0705JUD002375507",
      "ECLI:CE:ECHR:2000:0504JUD002834195"
    ]
  },
  {
    "ecli": "ECLI:CE:ECHR:2017:0919JUD003528911",
    "references": [
      "ECLI:CE:ECHR:2000:0504JUD002834195"
    ]
  },
  {
    "ecli": "ECLI:CE:ECHR:2017:1221JUD001724910",
    "references": []
  },
  {
    "ecli": "ECLI:CE:ECHR:2018:1108JUD000278212",
    "references": [
      "ECLI:CE:ECHR:2017:0627JUD000093113"
    ]
  },
  {
    "ecli": "ECLI:CE:ECHR:2018:1129JUD000444207",
    "references": []
  },
  {
    "ecli": "ECLI:CE:ECHR:2018:1211JUD003648007",
    "references": [
      "ECLI:CE:ECHR:2014:0717JUD004784808",
      "ECLI:CE:ECHR:2012:0626JUD002682806",
      "ECLI:CE:ECHR:2015:1204JUD004714306",
      "ECLI:CE:ECHR:2016:0705JUD004489810",
      "ECLI:CE:ECHR:2006:0316JUD005827800",
      "ECLI:CE:ECHR:2015:0616JUD004016706"
    ]
  },
  {
    "ecli": "ECLI:CE:ECHR:2018:1219JUD002045214",
    "references": [
      "ECLI:CE:ECHR:2012:0322JUD003007806",
      "ECLI:CE:ECHR:2015:0827JUD004647011"
    ]
  },
  {
    "ecli": "ECLI:CE:ECHR:2019:0129JUD000529414",
    "references": [
      "ECLI:CE:ECHR:2020:0707JUD000529414"
    ]
  },
  {
    "ecli": "ECLI:CE:ECHR:2019:0131JUD001805211",
    "references": [
      "ECLI:CE:ECHR:2006:0329JUD003681397",
      "ECLI:CE:ECHR:2010:0427JUD000000708",
      "ECLI:CE:ECHR:2010:0601JUD002297805",
      "ECLI:CE:ECHR:2016:0426JUD001051110"
    ]
  },
  {
    "ecli": "ECLI:CE:ECHR:2019:0307JUD005450308",
    "references": []
  },
  {
    "ecli": "ECLI:CE:ECHR:2020:0109JUD005648309",
    "references": []
  },
  {
    "ecli": "ECLI:CE:ECHR:2020:0213JUD000867515",
    "references": [
      "ECLI:CE:ECHR:2011:0707JUD005572107",
      "ECLI:CE:ECHR:2004:0708JUD004878799",
      "ECLI:CE:ECHR:2009:1015JUD001705606",
      "ECLI:CE:ECHR:2011:0121JUD003069609",
      "ECLI:CE:ECHR:2012:0223JUD002776509"
    ]
  },
  {
    "ecli": "ECLI:CE:ECHR:2020:0707JUD000529414",
    "references": [
      "ECLI:CE:ECHR:2018:1211JUD003648007",
      "ECLI:CE:ECHR:2014:0717JUD004784808",
      "ECLI:CE:ECHR:2008:0429JUD001337805",
      "ECLI:CE:ECHR:2019:0129JUD000529414"
    ]
  },
  {
    "ecli": "ECLI:CE:ECHR:2020:1222JUD001430517",
    "references": [
      "ECLI:CE:ECHR:2019:0131JUD001805211",
      "ECLI:CE:ECHR:2010:0427JUD000000708",
      "ECLI:CE:ECHR:2006:0329JUD003681397",
      "ECLI:CE:ECHR:2017:0627JUD000093113",
      "ECLI:CE:ECHR:2018:1219JUD002045214",
      "ECLI:CE:ECHR:2006:0316JUD005827800",
      "ECLI:CE:ECHR:2010:0601JUD002297805",
      "ECLI:CE:ECHR:2000:0504JUD002834195",
      "ECLI:CE:ECHR:2015:1204JUD004714306",
      "ECLI:CE:ECHR:2004:0708JUD004878799",
      "ECLI:CE:ECHR:2016:0705JUD002375507",
      "ECLI:CE:ECHR:2012:0626JUD002682806"
    ]
  },
  {
    "ecli": "ECLI:CE:ECHR:2021:0204JUD003999717",
    "references": [
      "ECLI:CE:ECHR:2014:0717JUD004784808"
    ]
  },
  {
    "ecli": "ECLI:CE:ECHR:2021:0413JUD000008017",
    "references": [
      "ECLI:CE:ECHR:2006:0329JUD003681397",
      "ECLI:CE:ECHR:2016:0705JUD002375507",
      "ECLI:CE:ECHR:2020:1222JUD001430517",
      "ECLI:CE:ECHR:2012:0626JUD002682806",
      "ECLI:CE:ECHR:2019:0131JUD001805211",
      "ECLI:CE:ECHR:2010:0601JUD002297805",
      "ECLI:CE:ECHR:2004:0708JUD004878799"
    ]
  },
  {
    "ecli": "ECLI:CE:ECHR:2021:0525JUD005817013",
    "references": [
      "ECLI:CE:ECHR:2021:0525JUD003525208",
      "ECLI:CE:ECHR:2000:0504JUD002834195",
      "ECLI:CE:ECHR:2015:1204JUD004714306",
      "ECLI:CE:ECHR:2012:0731JUD004002003",
      "ECLI:CE:ECHR:2011:0707JUD005572107"
    ]
  },
  {
    "ecli": "ECLI:CE:ECHR:2021:0525JUD003525208",
    "references": [
      "ECLI:CE:ECHR:2000:0504JUD002834195",
      "ECLI:CE:ECHR:2015:1204JUD004714306"
    ]
  },
  {
    "ecli": "ECLI:CE:ECHR:2022:0630JUD006165716",
    "references": []
  },
  {
    "ecli": "ECLI:CE:ECHR:2022:0728JUD005502517",
    "references": [
      "ECLI:CE:ECHR:2014:0717JUD004784808"
    ]
  },
  {
    "ecli": "ECLI:CE:ECHR:2022:0914JUD002438419",
    "references": [
      "ECLI:CE:ECHR:2012:0731JUD004002003",
      "ECLI:CE:ECHR:2015:0605JUD004604314",
      "ECLI:CE:ECHR:2011:0707JUD005572107",
      "ECLI:CE:ECHR:2012:0223JUD002776509",
      "ECLI:CE:ECHR:2012:0912JUD001059308",
      "ECLI:CE:ECHR:2014:0717JUD004784808",
      "ECLI:CE:ECHR:2004:0708JUD004878799"
    ]
  },
  {
    "ecli": "ECLI:CE:ECHR:2022:1108JUD007472917",
    "references": [
      "ECLI:CE:ECHR:2014:0128JUD003581009",
      "ECLI:CE:ECHR:2018:1108JUD000278212"
    ]
  },
  {
    "ecli": "ECLI:CE:ECHR:2023:0117JUD004079210",
    "references": [
      "ECLI:CE:ECHR:1999:0928JUD002811495",
      "ECLI:CE:ECHR:2020:0707JUD000529414",
      "ECLI:CE:ECHR:2006:0329JUD003681397",
      "ECLI:CE:ECHR:2014:0701JUD004383511",
      "ECLI:CE:ECHR:2012:0322JUD003007806",
      "ECLI:CE:ECHR:2010:0427JUD000000708",
      "ECLI:CE:ECHR:2019:0129JUD000529414",
      "ECLI:CE:ECHR:2012:0223JUD002776509",
      "ECLI:CE:ECHR:2017:0627JUD000093113",
      "ECLI:CE:ECHR:2014:0717JUD004784808",
      "ECLI:CE:ECHR:2016:0705JUD002375507"
    ]
  },
  {
    "ecli": "ECLI:CE:ECHR:2023:0216JUD000721813",
    "references": []
  },
  {
    "ecli": "ECLI:CE:ECHR:2023:1127JUD002188120",
    "references": [
      "ECLI:CE:ECHR:2008:0429JUD001337805",
      "ECLI:CE:ECHR:2015:0605JUD004604314",
      "ECLI:CE:ECHR:2014:0701JUD004383511",
      "ECLI:CE:ECHR:2015:0827JUD004647011",
      "ECLI:CE:ECHR:2014:0717JUD004784808",
      "ECLI:CE:ECHR:2006:0316JUD005827800",
      "ECLI:CE:ECHR:2010:0427JUD000000708"
    ]
  },
  {
    "ecli": "ECLI:CE:ECHR:2024:0123JUD002465019",
    "references": [
      "ECLI:CE:ECHR:2011:0121JUD003069609"
    ]
  },
  {
    "ecli": "ECLI:CE:ECHR:2024:0409JUD005360020",
    "references": [
      "ECLI:CE:ECHR:2015:0605JUD004604314",
      "ECLI:CE:ECHR:2012:0223JUD002776509",
      "ECLI:CE:ECHR:2019:0129JUD000529414",
      "ECLI:CE:ECHR:1999:1028JUD002834295",
      "ECLI:CE:ECHR:2011:0121JUD003069609",
      "ECLI:CE:ECHR:2020:0707JUD000529414",
      "ECLI:CE:ECHR:2010:0427JUD000000708",
      "ECLI:CE:ECHR:2015:1204JUD004714306",
      "ECLI:CE:ECHR:2008:0429JUD001337805",
      "ECLI:CE:ECHR:2014:0701JUD004383511",
      "ECLI:CE:ECHR:2014:0128JUD003581009",
      "ECLI:CE:ECHR:2014:0717JUD004784808"
    ]
  },
  {
    "ecli": "ECLI:CE:ECHR:2024:0917JUD001554120",
    "references": [
      "ECLI:CE:ECHR:2023:1127JUD002188120",
      "ECLI:CE:ECHR:2016:0426JUD001051110",
      "ECLI:CE:ECHR:2018:1219JUD002045214",
      "ECLI:CE:ECHR:2015:0605JUD004604314"
    ]
  }
]