[
  {
    "ecli": "ECLI:CE:ECHR:1995:1027JUD001669690",
    "references": []
  },
  {
    "ecli": "ECLI:CE:ECHR:1999:0401JUD002778195",
    "references": []
  },
  {
    "ecli": "ECLI:CE:ECHR:1999:0705JUD003153496",
    "references": []
  },
  {
    "ecli": "ECLI:CE:ECHR:1999:0706JUD003505297",
    "references": []
  },
  {
    "ecli": "ECLI:CE:ECHR:1999:1005JUD004029398",
    "references": []
  },
  {
    "ecli": "ECLI:CE:ECHR:1999:1019JUD004250098",
    "references": []
  },
  {
    "ecli": "ECLI:CE:ECHR:1999:1026JUD004028298",
    "references": []
  },
  {
    "ecli": "ECLI:CE:ECHR:1999:1214JUD004183298",
    "references": []
  },
  {
    "ecli": "ECLI:CE:ECHR:2000:0229JUD004359798",
    "references": []
  },
  {
    "ecli": "ECLI:CE:ECHR:2000:0316JUD002314493",
    "references": []
  },
  {
    "ecli": "ECLI:CE:ECHR:2000:0321JUD004093998",
    "references": []
  },
  {
    "ecli": "ECLI:CE:ECHR:2000:0404JUD003374496",
    "references": []
  },
  {
    "ecli": "ECLI:CE:ECHR:2000:0405JUD003438297",
    "references": []
  },
  {
    "ecli": "ECLI:CE:ECHR:2000:0405JUD004095698",
    "references": []
  },
  {
    "ecli": "ECLI:CE:ECHR:2000:0405JUD004096098",
    "references": []
  },
  {
    "ecli": "ECLI:CE:ECHR:2000:0406JUD002764495",
    "references": []
  },
  {
    "ecli": "ECLI:CE:ECHR:2000:0606JUD003652597",
    "references": []
  },
  {
    "ecli": "ECLI:CE:ECHR:2000:0622JUD004301498",
    "references": []
  },
  {
    "ecli": "ECLI:CE:ECHR:2000:0622JUD004303798",
    "references": []
  },
  {
    "ecli": "ECLI:CE:ECHR:2000:0622JUD004302198",
    "references": []
  },
  {
    "ecli": "ECLI:CE:ECHR:2000:0622JUD004299098",
    "references": []
  },
  {
    "ecli": "ECLI:CE:ECHR:2000:0622JUD004303498",
    "references": []
  },
  {
    "ecli": "ECLI:CE:ECHR:2000:0622JUD004299798",
    "references": []
  },
  {
    "ecli": "ECLI:CE:ECHR:2000:0622JUD004301698",
    "references": []
  },
  {
    "ecli": "ECLI:CE:ECHR:2000:0622JUD004306198",
    "references": []
  },
  {
    "ecli": "ECLI:CE:ECHR:2000:0622JUD004306898",
    "references": []
  },
  {
    "ecli": "ECLI:CE:ECHR:2000:0622JUD004303098",
    "references": []
  },
  {
    "ecli": "ECLI:CE:ECHR:2000:0622JUD004310198",
    "references": []
  },
  {
    "ecli": "ECLI:CE:ECHR:2000:0622JUD004307798",
    "references": []
  },
  {
    "ecli": "ECLI:CE:ECHR:2000:0627JUD002741795",
    "references": []
  },
  {
    "ecli": "ECLI:CE:ECHR:2000:0706JUD004373798",
    "references": []
  },
  {
    "ecli": "ECLI:CE:ECHR:2000:1012JUD004507398",
    "references": []
  },
  {
    "ecli": "ECLI:CE:ECHR:2000:1017JUD004435598",
    "references": []
  },
  {
    "ecli": "ECLI:CE:ECHR:2000:1116JUD002498994",
    "references": []
  },
  {
    "ecli": "ECLI:CE:ECHR:2000:1219JUD003418696",
    "references": []
  },
  {
    "ecli": "ECLI:CE:ECHR:2000:0525JUD003836697",
    "references": []
  },
  {
    "ecli": "ECLI:CE:ECHR:2001:0109JUD004180798",
    "references": []
  },
  {
    "ecli": "ECLI:CE:ECHR:2001:0301JUD002770095",
    "references": []
  },
  {
    "ecli": "ECLI:CE:ECHR:2001:0320JUD003172596",
    "references": []
  },
  {
    "ecli": "ECLI:CE:ECHR:2001:0412JUD004101898",
    "references": []
  },
  {
    "ecli": "ECLI:CE:ECHR:2001:0426JUD004816799",
    "references": []
  },
  {
    "ecli": "ECLI:CE:ECHR:2001:0522JUD003045396",
    "references": []
  },
  {
    "ecli": "ECLI:CE:ECHR:2001:0523JUD002531694",
    "references": []
  },
  {
    "ecli": "ECLI:CE:ECHR:2001:0614JUD003468697",
    "references": []
  },
  {
    "ecli": "ECLI:CE:ECHR:2001:0626JUD003745397",
    "references": []
  },
  {
    "ecli": "ECLI:CE:ECHR:2001:0710JUD002494694",
    "references": []
  },
  {
    "ecli": "ECLI:CE:ECHR:2001:0717JUD002986696",
    "references": []
  },
  {
    "ecli": "ECLI:CE:ECHR:2001:1004JUD003240496",
    "references": []
  },
  {
    "ecli": "ECLI:CE:ECHR:2001:1004JUD004928199",
    "references": []
  },
  {
    "ecli": "ECLI:CE:ECHR:2001:1011JUD005134299",
    "references": []
  },
  {
    "ecli": "ECLI:CE:ECHR:2001:1025JUD004624899",
    "references": []
  },
  {
    "ecli": "ECLI:CE:ECHR:2001:1030JUD002949595",
    "references": []
  },
  {
    "ecli": "ECLI:CE:ECHR:2001:1106JUD003095396",
    "references": []
  },
  {
    "ecli": "ECLI:CE:ECHR:2001:1203JUD003236396",
    "references": []
  },
  {
    "ecli": "ECLI:CE:ECHR:2001:1203JUD003724297",
    "references": []
  },
  {
    "ecli": "ECLI:CE:ECHR:2002:0226JUD002493294",
    "references": []
  },
  {
    "ecli": "ECLI:CE:ECHR:2002:0409JUD004479198",
    "references": []
  },
  {
    "ecli": "ECLI:CE:ECHR:2002:0514JUD003298596",
    "references": [
      "ECLI:CE:ECHR:2000:0316JUD002314493"
    ]
  },
  {
    "ecli": "ECLI:CE:ECHR:2002:0618JUD003649997",
    "references": []
  },
  {
    "ecli": "ECLI:CE:ECHR:2002:0620JUD002633795",
    "references": []
  },
  {
    "ecli": "ECLI:CE:ECHR:2002:0620JUD003507697",
    "references": [
      "ECLI:CE:ECHR:2000:0316JUD002314493",
      "ECLI:CE:ECHR:2002:0514JUD003298596"
    ]
  },
  {
    "ecli": "ECLI:CE:ECHR:2002:0627JUD002228193",
    "references": []
  },
  {
    "ecli": "ECLI:CE:ECHR:2002:0627JUD003505097",
    "references": []
  },
  {
    "ecli": "ECLI:CE:ECHR:2002:0704JUD005277299",
    "references": []
  },
  {
    "ecli": "ECLI:CE:ECHR:2002:0711JUD003209796",
    "references": []
  },
  {
    "ecli": "ECLI:CE:ECHR:2002:0716JUD004729399",
    "references": []
  },
  {
    "ecli": "ECLI:CE:ECHR:2002:0716JUD002928995",
    "references": []
  },
  {
    "ecli": "ECLI:CE:ECHR:2002:0718JUD003841597",
    "references": []
  },
  {
    "ecli": "ECLI:CE:ECHR:2002:0723JUD003879497",
    "references": []
  },
  {
    "ecli": "ECLI:CE:ECHR:2002:1017JUD003323496",
    "references": []
  },
  {
    "ecli": "ECLI:CE:ECHR:2002:1017JUD003966898",
    "references": []
  },
  {
    "ecli": "ECLI:CE:ECHR:2002:1107JUD003804397",
    "references": []
  },
  {
    "ecli": "ECLI:CE:ECHR:2002:1107JUD003611297",
    "references": []
  },
  {
    "ecli": "ECLI:CE:ECHR:2002:1115JUD004949799",
    "references": []
  },
  {
    "ecli": "ECLI:CE:ECHR:2002:1126JUD004126398",
    "references": []
  },
  {
    "ecli": "ECLI:CE:ECHR:2003:0109JUD003939298",
    "references": []
  },
  {
    "ecli": "ECLI:CE:ECHR:2003:0109JUD004533099",
    "references": []
  },
  {
    "ecli": "ECLI:CE:ECHR:2003:0225JUD003226796",
    "references": []
  },
  {
    "ecli": "ECLI:CE:ECHR:2003:0227JUD005499900",
    "references": []
  },
  {
    "ecli": "ECLI:CE:ECHR:2003:0325JUD004364998",
    "references": []
  },
  {
    "ecli": "ECLI:CE:ECHR:2003:0410JUD004361698",
    "references": []
  },
  {
    "ecli": "ECLI:CE:ECHR:2003:0422JUD002851695",
    "references": []
  },
  {
    "ecli": "ECLI:CE:ECHR:2003:0429JUD002849295",
    "references": []
  },
  {
    "ecli": "ECLI:CE:ECHR:2003:0506JUD002630795",
    "references": [
      "ECLI:CE:ECHR:2001:0626JUD003745397"
    ]
  },
  {
    "ecli": "ECLI:CE:ECHR:2003:0617JUD003184596",
    "references": []
  },
  {
    "ecli": "ECLI:CE:ECHR:2003:0624JUD002986396",
    "references": []
  },
  {
    "ecli": "ECLI:CE:ECHR:2003:0619JUD003227096",
    "references": [
      "ECLI:CE:ECHR:2000:0405JUD003438297"
    ]
  },
  {
    "ecli": "ECLI:CE:ECHR:2003:0729JUD003838297",
    "references": []
  },
  {
    "ecli": "ECLI:CE:ECHR:2003:0724JUD004001698",
    "references": [
      "ECLI:CE:ECHR:2003:0109JUD004533099",
      "ECLI:CE:ECHR:2003:0429JUD002849295"
    ]
  },
  {
    "ecli": "ECLI:CE:ECHR:2003:0923JUD003187996",
    "references": []
  },
  {
    "ecli": "ECLI:CE:ECHR:2003:1125JUD003543097",
    "references": []
  },
  {
    "ecli": "ECLI:CE:ECHR:2003:1204JUD004256098",
    "references": []
  },
  {
    "ecli": "ECLI:CE:ECHR:2003:1216JUD005708000",
    "references": []
  },
  {
    "ecli": "ECLI:CE:ECHR:2004:0205JUD005744800",
    "references": []
  },
  {
    "ecli": "ECLI:CE:ECHR:2004:0311JUD006787301",
    "references": []
  },
  {
    "ecli": "ECLI:CE:ECHR:2004:0408JUD002514294",
    "references": []
  },
  {
    "ecli": "ECLI:CE:ECHR:2004:0615JUD004863099",
    "references": []
  },
  {
    "ecli": "ECLI:CE:ECHR:2004:0617JUD005827800",
    "references": []
  },
  {
    "ecli": "ECLI:CE:ECHR:2004:0624JUD007044601",
    "references": []
  },
  {
    "ecli": "ECLI:CE:ECHR:2004:0708JUD007430901",
    "references": []
  },
  {
    "ecli": "ECLI:CE:ECHR:2004:0713JUD003704797",
    "references": []
  },
  {
    "ecli": "ECLI:CE:ECHR:2004:0729JUD005346899",
    "references": []
  },
  {
    "ecli": "ECLI:CE:ECHR:2004:1021JUD000446902",
    "references": []
  },
  {
    "ecli": "ECLI:CE:ECHR:2004:1102JUD002829495",
    "references": []
  },
  {
    "ecli": "ECLI:CE:ECHR:2004:1028JUD004817399",
    "references": []
  },
  {
    "ecli": "ECLI:CE:ECHR:2004:1209JUD000951402",
    "references": []
  },
  {
    "ecli": "ECLI:CE:ECHR:2004:1222JUD000976102",
    "references": []
  },
  {
    "ecli": "ECLI:CE:ECHR:2005:0210JUD002780602",
    "references": []
  },
  {
    "ecli": "ECLI:CE:ECHR:2005:0301JUD005348799",
    "references": [
      "ECLI:CE:ECHR:2003:0506JUD002630795"
    ]
  },
  {
    "ecli": "ECLI:CE:ECHR:2005:0329JUD007271301",
    "references": []
  },
  {
    "ecli": "ECLI:CE:ECHR:2005:0407JUD006930801",
    "references": []
  },
  {
    "ecli": "ECLI:CE:ECHR:2005:0628JUD005827400",
    "references": []
  },
  {
    "ecli": "ECLI:CE:ECHR:2005:0705JUD004113898",
    "references": []
  },
  {
    "ecli": "ECLI:CE:ECHR:2005:0928JUD003144396",
    "references": []
  },
  {
    "ecli": "ECLI:CE:ECHR:2005:0929JUD002514903",
    "references": [
      "ECLI:CE:ECHR:2003:0506JUD002630795",
      "ECLI:CE:ECHR:2001:0626JUD003745397",
      "ECLI:CE:ECHR:2005:0301JUD005348799"
    ]
  },
  {
    "ecli": "ECLI:CE:ECHR:2005:1025JUD005914000",
    "references": []
  },
  {
    "ecli": "ECLI:CE:ECHR:2005:1027JUD006110400",
    "references": []
  },
  {
    "ecli": "ECLI:CE:ECHR:2005:1117JUD002729503",
    "references": [
      "ECLI:CE:ECHR:2001:0626JUD003745397",
      "ECLI:CE:ECHR:2003:0506JUD002630795"
    ]
  },
  {
    "ecli": "ECLI:CE:ECHR:2005:1124JUD004942999",
    "references": [
      "ECLI:CE:ECHR:2003:0724JUD004001698"
    ]
  },
  {
    "ecli": "ECLI:CE:ECHR:2005:1124JUD006674201",
    "references": []
  },
  {
    "ecli": "ECLI:CE:ECHR:2006:0117JUD005469500",
    "references": []
  },
  {
    "ecli": "ECLI:CE:ECHR:2006:0202JUD003324396",
    "references": []
  },
  {
    "ecli": "ECLI:CE:ECHR:2006:0323JUD005900800",
    "references": []
  },
  {
    "ecli": "ECLI:CE:ECHR:2006:0406JUD003032496",
    "references": []
  },
  {
    "ecli": "ECLI:CE:ECHR:2006:0406JUD003154996",
    "references": []
  },
  {
    "ecli": "ECLI:CE:ECHR:2006:0406JUD003567197",
    "references": []
  },
  {
    "ecli": "ECLI:CE:ECHR:2006:0413JUD000511703",
    "references": []
  },
  {
    "ecli": "ECLI:CE:ECHR:2006:0615JUD005882200",
    "references": [
      "ECLI:CE:ECHR:2007:0115JUD006065400",
      "ECLI:CE:ECHR:2004:0617JUD005827800"
    ]
  },
  {
    "ecli": "ECLI:CE:ECHR:2006:0621JUD001181003",
    "references": [
      "ECLI:CE:ECHR:2006:0621JUD000151303"
    ]
  },
  {
    "ecli": "ECLI:CE:ECHR:2006:0621JUD000151303",
    "references": []
  },
  {
    "ecli": "ECLI:CE:ECHR:2006:0622JUD005964300",
    "references": [
      "ECLI:CE:ECHR:2007:0115JUD006065400",
      "ECLI:CE:ECHR:2007:1207JUD005964300",
      "ECLI:CE:ECHR:2006:0615JUD005882200"
    ]
  },
  {
    "ecli": "ECLI:CE:ECHR:2006:0713JUD004099698",
    "references": []
  },
  {
    "ecli": "ECLI:CE:ECHR:2006:0718JUD005350799",
    "references": [
      "ECLI:CE:ECHR:2003:0506JUD002630795"
    ]
  },
  {
    "ecli": "ECLI:CE:ECHR:2006:1010JUD006949801",
    "references": []
  },
  {
    "ecli": "ECLI:CE:ECHR:2006:1106JUD004457498",
    "references": []
  },
  {
    "ecli": "ECLI:CE:ECHR:2007:0115JUD006065400",
    "references": [
      "ECLI:CE:ECHR:2006:0622JUD005964300",
      "ECLI:CE:ECHR:2001:1011JUD005134299",
      "ECLI:CE:ECHR:2007:1207JUD005964300",
      "ECLI:CE:ECHR:2006:0615JUD005882200"
    ]
  },
  {
    "ecli": "ECLI:CE:ECHR:2007:0426JUD005788400",
    "references": [
      "ECLI:CE:ECHR:2003:0506JUD002630795",
      "ECLI:CE:ECHR:2005:0301JUD005348799",
      "ECLI:CE:ECHR:2006:0718JUD005350799",
      "ECLI:CE:ECHR:2005:0929JUD002514903"
    ]
  },
  {
    "ecli": "ECLI:CE:ECHR:2007:0710JUD003980605",
    "references": []
  },
  {
    "ecli": "ECLI:CE:ECHR:2007:0927JUD000630105",
    "references": [
      "ECLI:CE:ECHR:2005:0929JUD002514903",
      "ECLI:CE:ECHR:2001:0626JUD003745397",
      "ECLI:CE:ECHR:2003:0506JUD002630795"
    ]
  },
  {
    "ecli": "ECLI:CE:ECHR:2007:1108JUD003027303",
    "references": []
  },
  {
    "ecli": "ECLI:CE:ECHR:2007:1207JUD005964300",
    "references": [
      "ECLI:CE:ECHR:2007:0115JUD006065400",
      "ECLI:CE:ECHR:2006:0622JUD005964300"
    ]
  },
  {
    "ecli": "ECLI:CE:ECHR:2008:0408JUD004038706",
    "references": [
      "ECLI:CE:ECHR:2003:0506JUD002630795"
    ]
  },
  {
    "ecli": "ECLI:CE:ECHR:2008:0428JUD003501497",
    "references": [
      "ECLI:CE:ECHR:2005:0928JUD003144396"
    ]
  },
  {
    "ecli": "ECLI:CE:ECHR:2008:0529JUD000183904",
    "references": [
      "ECLI:CE:ECHR:2005:0210JUD002780602"
    ]
  },
  {
    "ecli": "ECLI:CE:ECHR:2008:0603JUD000562903",
    "references": []
  },
  {
    "ecli": "ECLI:CE:ECHR:2008:0624JUD000366903",
    "references": [
      "ECLI:CE:ECHR:2004:0617JUD005827800"
    ]
  },
  {
    "ecli": "ECLI:CE:ECHR:2008:0918JUD002328604",
    "references": [
      "ECLI:CE:ECHR:2005:0210JUD002780602"
    ]
  },
  {
    "ecli": "ECLI:CE:ECHR:2008:1003JUD004457498",
    "references": [
      "ECLI:CE:ECHR:2007:0115JUD006065400",
      "ECLI:CE:ECHR:2006:0615JUD005882200",
      "ECLI:CE:ECHR:2005:0928JUD003144396",
      "ECLI:CE:ECHR:2008:0428JUD003501497"
    ]
  },
  {
    "ecli": "ECLI:CE:ECHR:2008:1106JUD000301304",
    "references": [
      "ECLI:CE:ECHR:2005:0210JUD002780602"
    ]
  },
  {
    "ecli": "ECLI:CE:ECHR:2009:0303JUD003645802",
    "references": []
  },
  {
    "ecli": "ECLI:CE:ECHR:2009:0330JUD001932402",
    "references": [
      "ECLI:CE:ECHR:2003:0724JUD004001698"
    ]
  },
  {
    "ecli": "ECLI:CE:ECHR:2009:0423JUD003615604",
    "references": []
  },
  {
    "ecli": "ECLI:CE:ECHR:2009:0730JUD006733601",
    "references": [
      "ECLI:CE:ECHR:2003:0724JUD004001698"
    ]
  },
  {
    "ecli": "ECLI:CE:ECHR:2009:0918JUD001606490",
    "references": [
      "ECLI:CE:ECHR:2005:0301JUD005348799"
    ]
  },
  {
    "ecli": "ECLI:CE:ECHR:2010:0720JUD002542405",
    "references": [
      "ECLI:CE:ECHR:2003:0429JUD002849295"
    ]
  },
  {
    "ecli": "ECLI:CE:ECHR:2010:1007JUD003007806",
    "references": [
      "ECLI:CE:ECHR:2001:0626JUD003745397",
      "ECLI:CE:ECHR:2003:0724JUD004001698",
      "ECLI:CE:ECHR:2010:0107JUD002596504",
      "ECLI:CE:ECHR:2012:0322JUD003007806",
      "ECLI:CE:ECHR:2005:1124JUD004942999"
    ]
  },
  {
    "ecli": "ECLI:CE:ECHR:2010:0107JUD002596504",
    "references": [
      "ECLI:CE:ECHR:2003:0724JUD004001698",
      "ECLI:CE:ECHR:2005:1124JUD004942999",
      "ECLI:CE:ECHR:2003:0506JUD002630795"
    ]
  },
  {
    "ecli": "ECLI:CE:ECHR:2010:0119JUD001017105",
    "references": []
  },
  {
    "ecli": "ECLI:CE:ECHR:2010:0624JUD003014104",
    "references": [
      "ECLI:CE:ECHR:2003:0724JUD004001698",
      "ECLI:CE:ECHR:2006:0615JUD005882200"
    ]
  },
  {
    "ecli": "ECLI:CE:ECHR:2011:0517JUD002115104",
    "references": []
  },
  {
    "ecli": "ECLI:CE:ECHR:2011:0614JUD000995804",
    "references": [
      "ECLI:CE:ECHR:2007:0115JUD006065400",
      "ECLI:CE:ECHR:2006:0622JUD005964300",
      "ECLI:CE:ECHR:2006:0615JUD005882200",
      "ECLI:CE:ECHR:2007:1207JUD005964300"
    ]
  },
  {
    "ecli": "ECLI:CE:ECHR:2011:0621JUD007183101",
    "references": []
  },
  {
    "ecli": "ECLI:CE:ECHR:2011:0623JUD002049307",
    "references": [
      "ECLI:CE:ECHR:2010:0720JUD002542405"
    ]
  },
  {
    "ecli": "ECLI:CE:ECHR:2011:1011JUD000505610",
    "references": []
  },
  {
    "ecli": "ECLI:CE:ECHR:2012:0214JUD000639704",
    "references": [
      "ECLI:CE:ECHR:2011:0517JUD002115104"
    ]
  },
  {
    "ecli": "ECLI:CE:ECHR:2012:0322JUD003007806",
    "references": [
      "ECLI:CE:ECHR:2006:0615JUD005882200",
      "ECLI:CE:ECHR:2007:1207JUD005964300",
      "ECLI:CE:ECHR:2005:1124JUD004942999",
      "ECLI:CE:ECHR:2007:0115JUD006065400",
      "ECLI:CE:ECHR:2003:0724JUD004001698",
      "ECLI:CE:ECHR:2005:1025JUD005914000",
      "ECLI:CE:ECHR:2006:0622JUD005964300",
      "ECLI:CE:ECHR:2007:0710JUD003980605",
      "ECLI:CE:ECHR:2010:0107JUD002596504",
      "ECLI:CE:ECHR:2008:0428JUD003501497",
      "ECLI:CE:ECHR:2009:0730JUD006733601",
      "ECLI:CE:ECHR:2010:1007JUD003007806"
    ]
  },
  {
    "ecli": "ECLI:CE:ECHR:2012:0426JUD001227510",
    "references": []
  },
  {
    "ecli": "ECLI:CE:ECHR:2012:1218JUD006819410",
    "references": [
      "ECLI:CE:ECHR:2001:1011JUD005134299"
    ]
  },
  {
    "ecli": "ECLI:CE:ECHR:2013:0628JUD001657408",
    "references": []
  },
  {
    "ecli": "ECLI:CE:ECHR:2013:1114JUD001939111",
    "references": [
      "ECLI:CE:ECHR:2003:0506JUD002630795",
      "ECLI:CE:ECHR:2010:1007JUD003007806",
      "ECLI:CE:ECHR:2012:0322JUD003007806",
      "ECLI:CE:ECHR:2008:0408JUD004038706"
    ]
  },
  {
    "ecli": "ECLI:CE:ECHR:2014:0527JUD000992912",
    "references": [
      "ECLI:CE:ECHR:2007:0115JUD006065400"
    ]
  },
  {
    "ecli": "ECLI:CE:ECHR:2014:0710JUD001911309",
    "references": [
      "ECLI:CE:ECHR:2012:0322JUD003007806",
      "ECLI:CE:ECHR:2010:1007JUD003007806",
      "ECLI:CE:ECHR:2006:0615JUD005882200"
    ]
  },
  {
    "ecli": "ECLI:CE:ECHR:2014:1125JUD004855410",
    "references": []
  },
  {
    "ecli": "ECLI:CE:ECHR:2015:0127JUD003692510",
    "references": [
      "ECLI:CE:ECHR:2008:0428JUD003501497",
      "ECLI:CE:ECHR:2000:0316JUD002314493"
    ]
  },
  {
    "ecli": "ECLI:CE:ECHR:2015:0319JUD007005510",
    "references": []
  },
  {
    "ecli": "ECLI:CE:ECHR:2015:0408JUD007139812",
    "references": []
  },
  {
    "ecli": "ECLI:CE:ECHR:2015:0408JUD004934110",
    "references": []
  },
  {
    "ecli": "ECLI:CE:ECHR:2015:0611JUD003195311",
    "references": [
      "ECLI:CE:ECHR:2010:0107JUD002596504",
      "ECLI:CE:ECHR:2003:0506JUD002630795"
    ]
  },
  {
    "ecli": "ECLI:CE:ECHR:2015:0721JUD004185810",
    "references": [
      "ECLI:CE:ECHR:2010:0624JUD003014104"
    ]
  },
  {
    "ecli": "ECLI:CE:ECHR:2015:1022JUD000220411",
    "references": [
      "ECLI:CE:ECHR:2010:0107JUD002596504",
      "ECLI:CE:ECHR:2015:0611JUD003195311",
      "ECLI:CE:ECHR:2003:0506JUD002630795"
    ]
  },
  {
    "ecli": "ECLI:CE:ECHR:2015:1208JUD006011912",
    "references": [
      "ECLI:CE:ECHR:2005:0210JUD002780602"
    ]
  },
  {
    "ecli": "ECLI:CE:ECHR:2016:0323JUD004361111",
    "references": [
      "ECLI:CE:ECHR:2015:0408JUD007139812",
      "ECLI:CE:ECHR:2015:0408JUD004934110",
      "ECLI:CE:ECHR:2012:1218JUD006819410"
    ]
  },
  {
    "ecli": "ECLI:CE:ECHR:2016:0524JUD004168306",
    "references": [
      "ECLI:CE:ECHR:2004:0617JUD005827800"
    ]
  },
  {
    "ecli": "ECLI:CE:ECHR:2016:0705JUD004489810",
    "references": [
      "ECLI:CE:ECHR:2005:0929JUD002514903",
      "ECLI:CE:ECHR:2007:0426JUD005788400",
      "ECLI:CE:ECHR:2006:0718JUD005350799",
      "ECLI:CE:ECHR:2010:0107JUD002596504",
      "ECLI:CE:ECHR:2003:0506JUD002630795",
      "ECLI:CE:ECHR:2005:0928JUD003144396"
    ]
  },
  {
    "ecli": "ECLI:CE:ECHR:2016:0721JUD000906314",
    "references": []
  },
  {
    "ecli": "ECLI:CE:ECHR:2016:0901JUD004615411",
    "references": []
  },
  {
    "ecli": "ECLI:CE:ECHR:2016:0921JUD003803012",
    "references": [
      "ECLI:CE:ECHR:2006:0615JUD005882200",
      "ECLI:CE:ECHR:2016:0323JUD004361111",
      "ECLI:CE:ECHR:2012:1218JUD006819410",
      "ECLI:CE:ECHR:2007:0115JUD006065400",
      "ECLI:CE:ECHR:2015:0408JUD007139812"
    ]
  },
  {
    "ecli": "ECLI:CE:ECHR:2016:1004JUD004292708",
    "references": []
  },
  {
    "ecli": "ECLI:CE:ECHR:2016:1006JUD007643812",
    "references": []
  },
  {
    "ecli": "ECLI:CE:ECHR:2016:1115JUD005686108",
    "references": []
  },
  {
    "ecli": "ECLI:CE:ECHR:2016:1117JUD006012511",
    "references": [
      "ECLI:CE:ECHR:2016:0323JUD004361111",
      "ECLI:CE:ECHR:2011:0623JUD002049307",
      "ECLI:CE:ECHR:2010:0720JUD002542405"
    ]
  },
  {
    "ecli": "ECLI:CE:ECHR:2017:0223JUD004339509",
    "references": [
      "ECLI:CE:ECHR:2003:0506JUD002630795"
    ]
  },
  {
    "ecli": "ECLI:CE:ECHR:2017:1005JUD000100607",
    "references": [
      "ECLI:CE:ECHR:2016:0705JUD004489810",
      "ECLI:CE:ECHR:2003:0506JUD002630795"
    ]
  },
  {
    "ecli": "ECLI:CE:ECHR:2017:0530JUD007594711",
    "references": [
      "ECLI:CE:ECHR:2004:0617JUD005827800"
    ]
  },
  {
    "ecli": "ECLI:CE:ECHR:2017:1012JUD004685213",
    "references": [
      "ECLI:CE:ECHR:2016:0323JUD004361111",
      "ECLI:CE:ECHR:2008:0428JUD003501497",
      "ECLI:CE:ECHR:2005:0928JUD003144396"
    ]
  },
  {
    "ecli": "ECLI:CE:ECHR:2017:1026JUD002892309",
    "references": []
  },
  {
    "ecli": "ECLI:CE:ECHR:2017:1107JUD002943105",
    "references": [
      "ECLI:CE:ECHR:2003:0506JUD002630795"
    ]
  },
  {
    "ecli": "ECLI:CE:ECHR:2018:0417JUD005077513",
    "references": []
  },
  {
    "ecli": "ECLI:CE:ECHR:2018:1009JUD006941913",
    "references": []
  },
  {
    "ecli": "ECLI:CE:ECHR:2018:1113JUD002715307",
    "references": []
  },
  {
    "ecli": "ECLI:CE:ECHR:2018:1204JUD003552306",
    "references": [
      "ECLI:CE:ECHR:2003:0506JUD002630795"
    ]
  },
  {
    "ecli": "ECLI:CE:ECHR:2019:0416JUD002685606",
    "references": []
  },
  {
    "ecli": "ECLI:CE:ECHR:2020:0128JUD003183306",
    "references": []
  },
  {
    "ecli": "ECLI:CE:ECHR:2020:0130JUD000967115",
    "references": []
  },
  {
    "ecli": "ECLI:CE:ECHR:2020:0213JUD000867515",
    "references": [
      "ECLI:CE:ECHR:2010:0720JUD002542405",
      "ECLI:CE:ECHR:2016:0323JUD004361111",
      "ECLI:CE:ECHR:2016:1117JUD006012511"
    ]
  },
  {
    "ecli": "ECLI:CE:ECHR:2020:0326JUD004882608",
    "references": []
  },
  {
    "ecli": "ECLI:CE:ECHR:2020:1008JUD000722411",
    "references": [
      "ECLI:CE:ECHR:2003:0506JUD002630795"
    ]
  },
  {
    "ecli": "ECLI:CE:ECHR:2020:1117JUD000088919",
    "references": [
      "ECLI:CE:ECHR:2016:0323JUD004361111"
    ]
  },
  {
    "ecli": "ECLI:CE:ECHR:2021:0409JUD003037313",
    "references": [
      "ECLI:CE:ECHR:2009:0330JUD001932402",
      "ECLI:CE:ECHR:2014:1125JUD004855410"
    ]
  },
  {
    "ecli": "ECLI:CE:ECHR:2021:0921JUD007420916",
    "references": [
      "ECLI:CE:ECHR:2003:0506JUD002630795",
      "ECLI:CE:ECHR:2017:0223JUD004339509",
      "ECLI:CE:ECHR:2017:1005JUD000100607",
      "ECLI:CE:ECHR:2016:0705JUD004489810"
    ]
  },
  {
    "ecli": "ECLI:CE:ECHR:2021:1019JUD003146908",
    "references": [
      "ECLI:CE:ECHR:2007:0115JUD006065400"
    ]
  },
  {
    "ecli": "ECLI:CE:ECHR:2021:1209JUD005348713",
    "references": [
      "ECLI:CE:ECHR:2006:0622JUD005964300",
      "ECLI:CE:ECHR:2009:0303JUD003645802",
      "ECLI:CE:ECHR:2007:1207JUD005964300",
      "ECLI:CE:ECHR:2010:1007JUD003007806",
      "ECLI:CE:ECHR:2012:0322JUD003007806"
    ]
  },
  {
    "ecli": "ECLI:CE:ECHR:2022:0118JUD003007503",
    "references": []
  },
  {
    "ecli": "ECLI:CE:ECHR:2022:0531JUD007354817",
    "references": []
  },
  {
    "ecli": "ECLI:CE:ECHR:2022:0609JUD004927011",
    "references": [
      "ECLI:CE:ECHR:2013:0628JUD001657408",
      "ECLI:CE:ECHR:2016:0705JUD004489810",
      "ECLI:CE:ECHR:2007:0115JUD006065400",
      "ECLI:CE:ECHR:2021:0409JUD003037313",
      "ECLI:CE:ECHR:2004:0617JUD005827800",
      "ECLI:CE:ECHR:2012:0322JUD003007806",
      "ECLI:CE:ECHR:2010:1007JUD003007806",
      "ECLI:CE:ECHR:2005:0928JUD003144396"
    ]
  },
  {
    "ecli": "ECLI:CE:ECHR:2022:0721JUD000579717",
    "references": [
      "ECLI:CE:ECHR:2016:1117JUD006012511",
      "ECLI:CE:ECHR:2010:0720JUD002542405"
    ]
  },
  {
    "ecli": "ECLI:CE:ECHR:2022:0707JUD003271519",
    "references": [
      "ECLI:CE:ECHR:2016:0705JUD004489810",
      "ECLI:CE:ECHR:2010:0107JUD002596504",
      "ECLI:CE:ECHR:2017:1005JUD000100607"
    ]
  },
  {
    "ecli": "ECLI:CE:ECHR:2022:1103JUD002285420",
    "references": [
      "ECLI:CE:ECHR:2016:0323JUD004361111"
    ]
  },
  {
    "ecli": "ECLI:CE:ECHR:2022:1117JUD007485214",
    "references": [
      "ECLI:CE:ECHR:2016:1117JUD006012511"
    ]
  },
  {
    "ecli": "ECLI:CE:ECHR:2022:1206JUD005882910",
    "references": []
  },
  {
    "ecli": "ECLI:CE:ECHR:2022:1213JUD005686215",
    "references": [
      "ECLI:CE:ECHR:2000:0627JUD002741795"
    ]
  },
  {
    "ecli": "ECLI:CE:ECHR:2023:0117JUD004079210",
    "references": [
      "ECLI:CE:ECHR:2003:0724JUD004001698",
      "ECLI:CE:ECHR:2010:0624JUD003014104",
      "ECLI:CE:ECHR:2012:0322JUD003007806",
      "ECLI:CE:ECHR:2010:1007JUD003007806"
    ]
  },
  {
    "ecli": "ECLI:CE:ECHR:2023:0221JUD005204816",
    "references": []
  },
  {
    "ecli": "ECLI:CE:ECHR:2023:0302JUD005561717",
    "references": []
  },
  {
    "ecli": "ECLI:CE:ECHR:2023:0530JUD003995409",
    "references": []
  },
  {
    "ecli": "ECLI:CE:ECHR:2023:0712JUD000182806",
    "references": [
      "ECLI:CE:ECHR:2005:1124JUD004942999",
      "ECLI:CE:ECHR:2017:1005JUD000100607"
    ]
  },
  {
    "ecli": "ECLI:CE:ECHR:2024:1015JUD004075606",
    "references": []
  },
  {
    "ecli": "ECLI:CE:ECHR:2024:1015JUD000601616",
    "references": []
  },
  {
    "ecli": "ECLI:CE:ECHR:2025:0107JUD005901217",
    "references": []
  }
]